{
  "rank":   [
    {
      "rank":       1,
      "gift":       634033,
      "name":       "おとうふちゃん思「「"
    },
    {
      "rank":       2,
      "gift":       431010,
      "name":       "海神美羽9疹e+ 6 9"
    },
    {
      "rank":       3,
      "gift":       341045,
      "name":       "負い文"
    },
    {
      "rank":       4,
      "gift":       265206,
      "name":       "まりぃ@@明63アイコンガチイベ中内"
    },
    {
      "rank":       5,
      "gift":       237924,
      "name":       "み僧聖華"
    },
    {
      "rank":       6,
      "gift":       225628,
      "name":       "七月六日(月)"
    },
    {
      "rank":       7,
      "gift":       182161,
      "name":       "八前 ポルコ。勝つのは俺だ。"
    }
  ],
  "dates":   [
    "2026年06月30日 19:00",
    "2026年07月06日 23:59"
  ],
  "num":   47,
  "group":   "GR1",
  "gnum":   24,
  "img":   "20260630-GFT-A1_A2-GR1.png",
  "event":   "GFT",
  "min":   "A1",
  "max":   "A2"
}
