{
  "rank":   [
    {
      "rank":       1,
      "gift":       75513,
      "name":       "望奏多幸トブバナひゃっほい"
    },
    {
      "rank":       2,
      "gift":       47662,
      "name":       "印南 こもも@油断せずに行こう"
    },
    {
      "rank":       3,
      "gift":       45228,
      "name":       "NBIアHソツリルル-⑪ ゆまる⑨"
    },
    {
      "rank":       4,
      "gift":       31314,
      "name":       "ひろき@バーテンダー"
    },
    {
      "rank":       5,
      "gift":       29950,
      "name":       "藻近まいまい@本日十2代ねこ集め管"
    },
    {
      "rank":       6,
      "gift":       28132,
      "name":       "朝reggae幸Radyさおとめぇ洒"
    },
    {
      "rank":       7,
      "gift":       25264,
      "name":       "寝る子@本日イラストガチャ節"
    }
  ],
  "dates":   [
    "2025年9月16日 19:00",
    "2025年9月22日 23:59"
  ],
  "num":   76,
  "group":   "GR1",
  "gnum":   25,
  "img":   "20250916-ETC3-B2_B3-GR1.png",
  "event":   "ETC3",
  "min":   "B2",
  "max":   "B3"
}
