{
  "rank":   [
    {
      "rank":       1,
      "gift":       46074,
      "name":       "ペこちゃん公 *"
    },
    {
      "rank":       2,
      "gift":       22868,
      "name":       "愛空 MMSS >"
    },
    {
      "rank":       3,
      "gift":       17701,
      "name":       "さよ獲"
    },
    {
      "rank":       4,
      "gift":       15158,
      "name":       "やLana-うナ。。"
    },
    {
      "rank":       5,
      "gift":       14690,
      "name":       "youchaz 9 を"
    },
    {
      "rank":       6,
      "gift":       12512,
      "name":       "みいちゃん“人M"
    },
    {
      "rank":       7,
      "gift":       9756,
      "name":       "立競介共てつの落馬"
    },
    {
      "rank":       8,
      "gift":       9386,
      "name":       "白曽女・"
    }
  ],
  "dates":   [
    "2025年8月26日 19:00",
    "2025年9月1日 23:59"
  ],
  "num":   50,
  "img":   "20250826-ETC2-C1_C3.png",
  "event":   "ETC2",
  "min":   "C1",
  "max":   "C3"
}
