{
  "rank":   [
    {
      "rank":       1,
      "gift":       413719,
      "name":       "えど 色帯8バッジ背景1位77xl! る"
    },
    {
      "rank":       2,
      "gift":       330334,
      "name":       "あこ@ほんまに感謝しかない熟女〇"
    },
    {
      "rank":       3,
      "gift":       150677,
      "name":       "島 レモンティーKk⑤51プ60倫 を"
    },
    {
      "rank":       4,
      "gift":       144322,
      "name":       "まま w サリー・カナ加奈【感謝ウ】"
    },
    {
      "rank":       5,
      "gift":       60064,
      "name":       "くまベアー !! 旨委"
    },
    {
      "rank":       6,
      "gift":       57517,
      "name":       "SunnyHeart の"
    },
    {
      "rank":       7,
      "gift":       55570,
      "name":       "ec2ひみか沈バチ30個ガチイベ肩甲骨痛い"
    },
    {
      "rank":       8,
      "gift":       51743,
      "name":       "リハル,"
    }
  ],
  "dates":   [
    "2026年1月6日 19:00",
    "2026年1月12日 23:59"
  ],
  "num":   26,
  "img":   "20260106-FB-B1_B3.png",
  "event":   "FB",
  "min":   "B1",
  "max":   "B3"
}
