{
  "rank":   [
    {
      "rank":       1,
      "gift":       351977,
      "name":       "黒可MAA"
    },
    {
      "rank":       2,
      "gift":       167869,
      "name":       "基 を ⑯ugz/ 太 1周年イベミthx"
    },
    {
      "rank":       3,
      "gift":       137556,
      "name":       "りゅーま宣"
    },
    {
      "rank":       4,
      "gift":       128902,
      "name":       "9一周年イベ 名リツリッ"
    },
    {
      "rank":       5,
      "gift":       22845,
      "name":       "WTiara6卒業まで27日 夏"
    },
    {
      "rank":       6,
      "gift":       8315,
      "name":       "※ゅゆうぞう"
    },
    {
      "rank":       7,
      "gift":       13,
      "name":       "沈.oまいmai。 (3日30名集め筐)"
    }
  ],
  "dates":   [
    "2026年1月27日 19:00",
    "2026年2月2日 23:59"
  ],
  "num":   7,
  "img":   "20260127-1YA-B1_B3.png",
  "event":   "1YA",
  "min":   "B1",
  "max":   "B3"
}
